{
  "as_of": "2026-07-22",
  "base_currency": "CNY",
  "building_principal": 10000.0,
  "initial_build_percent": 20.0,
  "holdings": [
    {
      "fund_code": "012773",
      "name": "嘉实超短债债券A",
      "shares": null,
      "cost_basis": 2000.0,
      "target_percent": 51.0,
      "asset_class": "短债基金",
      "note": "已建仓短债；净值和份额待补充。"
    },
    {
      "fund_code": "160119",
      "name": "南方中证500ETF联接(LOF)A",
      "shares": null,
      "cost_basis": 500.0,
      "target_percent": 11.0,
      "asset_class": "A股宽基",
      "note": "中证500建仓"
    },
    {
      "fund_code": "016452",
      "name": "南方纳斯达克100指数发起(QDII)A",
      "shares": null,
      "cost_basis": 30.0,
      "target_percent": 3.0,
      "asset_class": "美股QDII",
      "note": "纳斯达克100建仓"
    },
    {
      "fund_code": "460300",
      "name": "华泰柏瑞沪深300ETF联接A",
      "shares": null,
      "cost_basis": 100.0,
      "target_percent": 27.0,
      "asset_class": "A股宽基",
      "note": "沪深300建仓"
    }
  ],
  "transactions": [
    {
      "transaction_id": "bootstrap-012773-2000",
      "idempotency_key": "bootstrap-012773-2000",
      "trade_date": "2026-07-01",
      "time": "2026-07-01T12:00:00+08:00",
      "side": "buy",
      "fund_code": "012773",
      "amount": 2000.0,
      "cost_delta": 2000.0,
      "shares": null,
      "nav": null,
      "note": "短债建仓（非定投）",
      "purpose": "bootstrap"
    },
    {
      "transaction_id": "3a45b5fd-9de0-4332-9d78-7c68b4de800f",
      "idempotency_key": "f27909e8b0d964b7842a981d",
      "trade_date": "2026-07-20",
      "time": "2026-07-20T13:58:13+08:00",
      "side": "buy",
      "fund_code": "160119",
      "amount": 500.0,
      "cost_delta": 500.0,
      "shares": null,
      "nav": null,
      "note": "中证500建仓",
      "purpose": "build"
    },
    {
      "transaction_id": "e2a9d865-3698-427d-912f-40f7934e47b5",
      "idempotency_key": "f64ab708f96d7e166c5b99b6",
      "trade_date": "2026-07-20",
      "time": "2026-07-20T14:01:14+08:00",
      "side": "buy",
      "fund_code": "016452",
      "amount": 10.0,
      "cost_delta": 10.0,
      "shares": null,
      "nav": null,
      "note": "纳斯达克100建仓",
      "purpose": "build"
    },
    {
      "transaction_id": "b060d26c-36bc-46b4-a8d5-e20ef19b3cee",
      "idempotency_key": "251c2a9b8c118e7f3e83fd66",
      "trade_date": "2026-07-21",
      "time": "2026-07-21T14:24:57+08:00",
      "side": "buy",
      "fund_code": "460300",
      "amount": 100.0,
      "cost_delta": 100.0,
      "shares": null,
      "nav": null,
      "note": "沪深300建仓",
      "purpose": "build"
    },
    {
      "transaction_id": "e41b2776-0382-45ee-a8cb-0db27b59ee94",
      "idempotency_key": "b843f948fd01f9107e7628ba",
      "trade_date": "2026-07-21",
      "time": "2026-07-21T14:24:57+08:00",
      "side": "buy",
      "fund_code": "016452",
      "amount": 10.0,
      "cost_delta": 10.0,
      "shares": null,
      "nav": null,
      "note": "纳斯达克100建仓",
      "purpose": "build"
    },
    {
      "transaction_id": "8b040c2c-de35-46c2-807d-1acaa63def8f",
      "idempotency_key": "525083ce646d0b83f62b6be1",
      "trade_date": "2026-07-22",
      "time": "2026-07-22T09:34:43+08:00",
      "side": "buy",
      "fund_code": "016452",
      "amount": 10.0,
      "cost_delta": 10.0,
      "shares": null,
      "nav": null,
      "note": "纳斯达克100建仓",
      "purpose": "build"
    }
  ]
}
